spata/__init__.py
spata-0.0.0.dist-info/licenses/LICENSE.txt
spata-0.0.0.dist-info/WHEEL
spata-0.0.0.dist-info/METADATA
spata-0.0.0.dist-info/RECORD
